cerebro/__init__.py
cerebro/api/__init__.py
cerebro/api/cerebro_server.py
cerebro/api/parsers.py
cerebro/api/restplus.py
cerebro/api/serializers.py
cerebro/api/endpoints/__init__.py
cerebro/api/endpoints/experiments.py
cerebro/api/endpoints/models.py
cerebro/api/endpoints/scripts.py
cerebro/backend/__init__.py
cerebro/backend/backend.py
cerebro/backend/codec.py
cerebro/backend/constants.py
cerebro/backend/host_hash.py
cerebro/backend/job_id.py
cerebro/backend/secret.py
cerebro/backend/settings.py
cerebro/backend/timeout.py
cerebro/backend/dask/__init__.py
cerebro/backend/spark/__init__.py
cerebro/backend/spark/backend.py
cerebro/backend/spark/service_common.py
cerebro/backend/spark/service_driver.py
cerebro/backend/spark/service_task.py
cerebro/backend/spark/util.py
cerebro/commons/__init__.py
cerebro/commons/constants.py
cerebro/commons/model_names.txt
cerebro/commons/util.py
cerebro/db/__init__.py
cerebro/db/dao.py
cerebro/keras/__init__.py
cerebro/keras/base.py
cerebro/keras/estimator.py
cerebro/keras/optimizer.py
cerebro/keras/params.py
cerebro/keras/tensorflow.py
cerebro/keras/dask/__init__.py
cerebro/keras/spark/__init__.py
cerebro/keras/spark/estimator.py
cerebro/keras/spark/params.py
cerebro/keras/spark/util.py
cerebro/standalone/__init__.py
cerebro/standalone/cerebro.py
cerebro/standalone/utils.py
cerebro/standalone/worker.py
cerebro/storage/__init__.py
cerebro/storage/base.py
cerebro/storage/hdfs.py
cerebro/storage/local.py
cerebro/tune/__init__.py
cerebro/tune/base.py
cerebro/tune/daemon.py
cerebro/tune/grid.py
cerebro/tune/tpe.py
cerebro_dl-1.1.1.dist-info/LICENSE
cerebro_dl-1.1.1.dist-info/METADATA
cerebro_dl-1.1.1.dist-info/WHEEL
cerebro_dl-1.1.1.dist-info/entry_points.txt
cerebro_dl-1.1.1.dist-info/top_level.txt
cerebro_dl-1.1.1.dist-info/RECORD
